morsecode_handler/__init__.py
morsecode_handler/__main__.py
morsecode_handler/core.py
morsecode_handler/exceptions.py
morsecode_handler-0.0.1.dist-info/licenses/LICENSE
morsecode_handler-0.0.1.dist-info/METADATA
morsecode_handler-0.0.1.dist-info/WHEEL
morsecode_handler-0.0.1.dist-info/entry_points.txt
morsecode_handler-0.0.1.dist-info/top_level.txt
morsecode_handler-0.0.1.dist-info/RECORD
