Metadata-Version: 2.4
Name: morsecode-handler
Version: 0.0.1
Summary: Encode and decode Morse code with custom errors, language JSON dictionaries, and CLI support.
Author-email: Ricardo <ricardo.lee.cm@gmail.com>
License: MIT
Project-URL: Homepage, https://github.com/mricardo888/morsecode
Project-URL: Repository, https://github.com/mricardo888/morsecode.git
Project-URL: Issues, https://github.com/mricardo888/morsecode/issues
Keywords: morse,morse code,encode,decode,cli,language,handler
Classifier: Development Status :: 5 - Production/Stable
Classifier: Intended Audience :: Developers
Classifier: Intended Audience :: Education
Classifier: License :: OSI Approved :: MIT License
Classifier: Programming Language :: Python :: 3
Classifier: Programming Language :: Python :: 3.7
Classifier: Programming Language :: Python :: 3.8
Classifier: Programming Language :: Python :: 3.9
Classifier: Programming Language :: Python :: 3.10
Classifier: Programming Language :: Python :: 3.11
Classifier: Programming Language :: Python :: 3.12
Classifier: Topic :: Utilities
Classifier: Topic :: Text Processing :: Linguistic
Requires-Python: >=3.7
License-File: LICENSE
Dynamic: license-file
